intedact/__init__.py
intedact/bivariate_eda_interact.py
intedact/bivariate_summaries.py
intedact/config.py
intedact/helper_plots.py
intedact/univariate_eda_interact.py
intedact/univariate_summaries.py
intedact/utils.py
intedact-0.1.0.dist-info/LICENSE
intedact-0.1.0.dist-info/METADATA
intedact-0.1.0.dist-info/WHEEL
intedact-0.1.0.dist-info/top_level.txt
intedact-0.1.0.dist-info/RECORD
