Metadata-Version: 2.1
Name: intedact
Version: 0.1.0
Summary: Interactive EDA visualizations in your jupyter notebook
Home-page: https://intedact.readthedocs.io/en/latest/index.html
Download-URL: https://github.com/mattboggess/intedact
Author: Matthew Boggess
Author-email: mattboggess7@gmail.com
Keywords: eda,data visualization,data science,pandas,data analysis,python
Requires-Python: >=3.6
License-File: LICENSE
Requires-Dist: numpy
Requires-Dist: pandas
Requires-Dist: plotly
Requires-Dist: plotnine
Requires-Dist: tldextract
Requires-Dist: nltk
Requires-Dist: ipywidgets
Requires-Dist: ipython
Requires-Dist: nbformat
